Metadata-Version: 2.1
Name: odoo14-addon-shopinvader_sale_packaging_wishlist
Version: 14.0.1.0.1.dev3
Summary: Add packaging information to wishlists
Home-page: https://github.com/shopinvader/odoo-shopinvader
Author: Camptocamp,Odoo Community Association (OCA)
Author-email: support@odoo-community.org
License: AGPL-3
Classifier: Programming Language :: Python
Classifier: Framework :: Odoo
Classifier: Framework :: Odoo :: 14.0
Classifier: License :: OSI Approved :: GNU Affero General Public License v3
Requires-Python: >=3.6
Requires-Dist: odoo14-addon-sale-product-set-packaging-qty
Requires-Dist: odoo14-addon-shopinvader-sale-packaging
Requires-Dist: odoo14-addon-shopinvader-wishlist
Requires-Dist: odoo <14.1dev,>=14.0a
